{
  "project_info": {
    "project_number": "728074998038",
    "project_id": "zylu-task",
    "storage_bucket": "zylu-task.appspot.com"
  },
  "client": [
    {
      "client_info": {
        "mobilesdk_app_id": "1:728074998038:android:58030d61c3e5e1f808c037",
        "android_client_info": {
          "package_name": "com.example.flutter_task_zylu"
        }
      },
      "oauth_client": [
        {
          "client_id": "728074998038-9pv4nnn4octe5freoodql23tg6d3uc75.apps.googleusercontent.com",
          "client_type": 3
        }
      ],
      "api_key": [
        {
          "current_key": "AIzaSyAjXaLK2rvr3YdfWWnHeefxJntY10KR9z0"
        }
      ],
      "services": {
        "appinvite_service": {
          "other_platform_oauth_client": [
            {
              "client_id": "728074998038-9pv4nnn4octe5freoodql23tg6d3uc75.apps.googleusercontent.com",
              "client_type": 3
            }
          ]
        }
      }
    }
  ],
  "configuration_version": "1"
}